{
    "Workloads": [
        {
            "Identifier": "Test New new",
            "AccessIP": "1234",
            "AccessPort": "1234",
            "Available": true,
            "AutoMigrate": false,
            "SharedDir": "/home/wolder/shared_storage",
            "Type": "Container",
            "Containerproperties": {
                "ContainerID": "sweet_noether",
                "Image": "pyserver",
                "Checkpoint": false,
                "NetworkSettings": null,
                "CheckpointIDs": null
            }
        }
    ]
}